turbo_queue/__init__.py
turbo_queue/_turbo_queue_kafka.py
turbo_queue/_turbo_queue_multi_task.py
turbo_queue/turbo_queue.py
turbo_queue-0.8.0.dist-info/METADATA
turbo_queue-0.8.0.dist-info/WHEEL
turbo_queue-0.8.0.dist-info/licenses/LICENSE
turbo_queue-0.8.0.dist-info/RECORD
