Metadata-Version: 2.1
Name: turbo-queue
Version: 0.8.0
Summary: A Python module to improve performance of multiprocessing queues
Project-URL: Homepage, https://github.com/davewat/turbo-queue
Project-URL: Bug Tracker, https://github.com/davewat/turbo-queue/issues
Author-email: Dave Waters <dave@1waters.com>
License-File: LICENSE
Classifier: License :: OSI Approved :: MIT License
Classifier: Operating System :: OS Independent
Classifier: Programming Language :: Python :: 3
Requires-Python: >=3.9
